qt_api/__init__.py
qt_api/qt.py
qt_api/utils.py
qt_api-0.2.5.dist-info/LICENSE
qt_api-0.2.5.dist-info/METADATA
qt_api-0.2.5.dist-info/WHEEL
qt_api-0.2.5.dist-info/top_level.txt
qt_api-0.2.5.dist-info/RECORD
