Metadata-Version: 2.1
Name: qt-api
Version: 0.2.5
Summary: Python wrapper for Questrade API
Author: Lyubomir Georgiev
License: Apache-2.0
Project-URL: Homepage, https://github.com/LVG77/qt-api
Project-URL: Changelog, https://github.com/LVG77/qt-api/releases
Project-URL: Issues, https://github.com/LVG77/qt-api/issues
Project-URL: CI, https://github.com/LVG77/qt-api/actions
Classifier: License :: OSI Approved :: Apache Software License
Requires-Python: >=3.8
License-File: LICENSE
Requires-Dist: httpx
Requires-Dist: pydantic
Requires-Dist: PyYAML
Provides-Extra: dev
Requires-Dist: pytest ; extra == 'dev'
Requires-Dist: ipykernel ; extra == 'dev'
Provides-Extra: test
Requires-Dist: pytest ; extra == 'test'
